BalanceEvolution/__init__.py
BalanceEvolution/mc.py
BalanceEvolution-0.11.dist-info/METADATA
BalanceEvolution-0.11.dist-info/WHEEL
BalanceEvolution-0.11.dist-info/top_level.txt
BalanceEvolution-0.11.dist-info/RECORD
