Metadata-Version: 2.1
Name: BalanceEvolution
Version: 0.11
Summary: Monte Carlo simulations of the trading account evolution based on the winning ratio and risk-reward relation of a trading plan.
Home-page: https://github.com/optimizedoptions/BalanceEvolution
Author: Optimized Options
License: UNKNOWN
Platform: UNKNOWN
Requires: scipy
Requires: numpy
Requires: matplotlib
